pylogger/__init__.py
pylogger/log_level.py
pylogger/logger.py
pylogging/__init__.py
pylogging/log_level.py
pylogging/logger.py
py_logging-1.0.2.dist-info/LICENSE
py_logging-1.0.2.dist-info/METADATA
py_logging-1.0.2.dist-info/WHEEL
py_logging-1.0.2.dist-info/top_level.txt
py_logging-1.0.2.dist-info/RECORD
