Metadata-Version: 2.1
Name: py-logging
Version: 1.0.2
Summary: Configurable and easy extendable python logger.
Home-page: https://github.com/Szczurowsky/py-logging
Author: Kamil Szczurowski
Author-email: kamil@szczurowsky.pl
License: MPL-2.0
Platform: UNKNOWN
License-File: LICENSE
